[
  {
    "maLop": "2024L10A1",
    "tenLop": "10A1",
    "tenHK": "HK1",
    "tenNamHoc": 2024
  },
  {
    "maLop": "2024L10A2",
    "tenLop": "10A2",
    "tenHK": "HK1",
    "tenNamHoc": 2024
  },
  {
    "maLop": "2024L11A1",
    "tenLop": "11A1",
    "tenHK": "HK1",
    "tenNamHoc": 2024
  },
  {
    "maLop": "2024L11A2",
    "tenLop": "11A2",
    "tenHK": "HK1",
    "tenNamHoc": 2024
  },
  {
    "maLop": "2024L12A1",
    "tenLop": "12A1",
    "tenHK": "HK1",
    "tenNamHoc": 2024
  },
  {
    "maLop": "2024L12A2",
    "tenLop": "12A2",
    "tenHK": "HK1",
    "tenNamHoc": 2024
  },
  {
    "maLop": "2024L10A1",
    "tenLop": "10A1",
    "tenHK": "HK2",
    "tenNamHoc": 2024
  },
  {
    "maLop": "2024L10A2",
    "tenLop": "10A2",
    "tenHK": "HK2",
    "tenNamHoc": 2024
  },
  {
    "maLop": "2024L11A1",
    "tenLop": "11A1",
    "tenHK": "HK2",
    "tenNamHoc": 2024
  },
  {
    "maLop": "2024L11A2",
    "tenLop": "11A2",
    "tenHK": "HK2",
    "tenNamHoc": 2024
  },
  {
    "maLop": "2024L12A1",
    "tenLop": "12A1",
    "tenHK": "HK2",
    "tenNamHoc": 2024
  },
  {
    "maLop": "2024L12A2",
    "tenLop": "12A2",
    "tenHK": "HK2",
    "tenNamHoc": 2024
  }
]